IntroductionToTouchdesigner/README.md
IntroductionToTouchdesigner/__init__.py
IntroductionToTouchdesigner/__main__.py
IntroductionToTouchdesigner/file.epub
IntroductionToTouchdesigner/index.html
IntroductionToTouchdesigner/css/__init__.py
IntroductionToTouchdesigner/css/annotations.css
IntroductionToTouchdesigner/css/main.css
IntroductionToTouchdesigner/css/normalize.css
IntroductionToTouchdesigner/css/popup.css
IntroductionToTouchdesigner/font/__init__.py
IntroductionToTouchdesigner/font/fontello.eot
IntroductionToTouchdesigner/font/fontello.svg
IntroductionToTouchdesigner/font/fontello.ttf
IntroductionToTouchdesigner/font/fontello.woff
IntroductionToTouchdesigner/img/__init__.py
IntroductionToTouchdesigner/img/annotator-glyph-sprite.png
IntroductionToTouchdesigner/img/annotator-icon-sprite.png
IntroductionToTouchdesigner/img/apple-touch-icon.png
IntroductionToTouchdesigner/img/cancelfullscreen.png
IntroductionToTouchdesigner/img/close.png
IntroductionToTouchdesigner/img/fullscreen.png
IntroductionToTouchdesigner/img/loader.gif
IntroductionToTouchdesigner/img/menu-icon.png
IntroductionToTouchdesigner/img/save.png
IntroductionToTouchdesigner/img/saved.png
IntroductionToTouchdesigner/img/settings-s.png
IntroductionToTouchdesigner/img/settings.png
IntroductionToTouchdesigner/img/star.png
IntroductionToTouchdesigner/js/__init__.py
IntroductionToTouchdesigner/js/epub.js
IntroductionToTouchdesigner/js/epub.min.js
IntroductionToTouchdesigner/js/epub.min.map
IntroductionToTouchdesigner/js/hooks.min.js
IntroductionToTouchdesigner/js/hooks.min.map
IntroductionToTouchdesigner/js/reader.js
IntroductionToTouchdesigner/js/reader.js.map
IntroductionToTouchdesigner/js/reader.min.js
IntroductionToTouchdesigner/js/reader.min.map
IntroductionToTouchdesigner/js/hooks/__init__.py
IntroductionToTouchdesigner/js/hooks/extensions/__init__.py
IntroductionToTouchdesigner/js/hooks/extensions/highlight.js
IntroductionToTouchdesigner/js/libs/__init__.py
introduction_to_touchdesigner-2024.3.4.0.dist-info/METADATA
introduction_to_touchdesigner-2024.3.4.0.dist-info/WHEEL
introduction_to_touchdesigner-2024.3.4.0.dist-info/entry_points.txt
introduction_to_touchdesigner-2024.3.4.0.dist-info/top_level.txt
introduction_to_touchdesigner-2024.3.4.0.dist-info/RECORD
